GatariAPI.py
gatariapi-0.1.0.dist-info/WHEEL
gatariapi-0.1.0.dist-info/METADATA
gatariapi-0.1.0.dist-info/RECORD
