Metadata-Version: 2.1
Name: gatariapi
Version: 0.1.0
Summary: API of Osu!Gatari for Python
Author: ChezZz
Author-email: egorchernobai@yandex.ru
Requires-Python: >=3.8,<4.0
Classifier: Programming Language :: Python :: 3
Classifier: Programming Language :: Python :: 3.8
Classifier: Programming Language :: Python :: 3.9
